{
  "kind": "collectionType",
  "collectionName": "provinces",
  "info": {
    "singularName": "province",
    "pluralName": "provinces",
    "displayName": "province",
    "description": ""
  },
  "options": {
    "draftAndPublish": false
  },
  "pluginOptions": {},
  "attributes": {
    "name": {
      "type": "string",
      "required": true
    },
    "code": {
      "type": "string",
      "required": true
    },
    "externalId": {
      "type": "string",
      "required": true
    }
  }
}
